{
  "workspace:undo-close-pane": [],
  "tag-pane:open": [
    {
      "modifiers": [
        "Alt",
        "Mod"
      ],
      "key": "T"
    }
  ],
  "table-editor-obsidian:move-row-down": [
    {
      "modifiers": [
        "Mod"
      ],
      "key": "ArrowDown"
    }
  ],
  "table-editor-obsidian:move-row-up": [
    {
      "modifiers": [
        "Mod"
      ],
      "key": "ArrowUp"
    }
  ],
  "table-editor-obsidian:move-column-left": [
    {
      "modifiers": [
        "Mod"
      ],
      "key": "ArrowLeft"
    }
  ],
  "table-editor-obsidian:move-column-right": [
    {
      "modifiers": [
        "Mod"
      ],
      "key": "ArrowRight"
    }
  ],
  "editor:swap-line-up": [
    {
      "modifiers": [
        "Alt"
      ],
      "key": "ArrowUp"
    }
  ],
  "outline:open": [],
  "app:toggle-left-sidebar": [
    {
      "modifiers": [
        "Mod",
        "Shift"
      ],
      "key": "L"
    }
  ],
  "obsidian-editor-shortcuts:selectLine": [
    {
      "modifiers": [
        "Mod"
      ],
      "key": "L"
    }
  ],
  "obsidian-hotkeys-for-templates:-模板-.md": [],
  "obsidian-hotkeys-for-templates:-Line-Break-.md": [
    {
      "modifiers": [
        "Mod",
        "Shift"
      ],
      "key": "Enter"
    }
  ],
  "obsidian-hotkeys-for-templates:-Math-Block-.md": [
    {
      "modifiers": [
        "Mod"
      ],
      "key": "M"
    }
  ],
  "obsidian-hotkeys-for-templates:-YAML-.md": [
    {
      "modifiers": [
        "Shift"
      ],
      "key": "Insert"
    }
  ],
  "url-into-selection:paste-url-into-selection": [
    {
      "modifiers": [
        "Mod",
        "Shift"
      ],
      "key": "V"
    }
  ],
  "app:go-forward": [
    {
      "modifiers": [
        "Alt"
      ],
      "key": "ArrowRight"
    }
  ],
  "app:go-back": [
    {
      "modifiers": [
        "Alt"
      ],
      "key": "ArrowLeft"
    }
  ],
  "obsidian-copy-block-link:copy-link-to-block": [
    {
      "modifiers": [
        "Mod",
        "Shift"
      ],
      "key": "C"
    }
  ],
  "obsidian-hotkeys-for-templates:-Chap-Break-.md": [
    {
      "modifiers": [
        "Alt"
      ],
      "key": "S"
    }
  ],
  "workspace:edit-file-title": [
    {
      "modifiers": [],
      "key": "F2"
    }
  ],
  "file-explorer:move-file": [
    {
      "modifiers": [
        "Mod",
        "Shift"
      ],
      "key": "X"
    }
  ],
  "app:toggle-right-sidebar": [
    {
      "modifiers": [
        "Mod",
        "Shift"
      ],
      "key": "R"
    }
  ],
  "table-editor-obsidian:table-control-bar": [],
  "obsidian-hotkeys-for-templates:FORALL.md": [
    {
      "modifiers": [
        "Alt"
      ],
      "key": "A"
    }
  ],
  "obsidian-hotkeys-for-templates:EXISTS.md": [
    {
      "modifiers": [
        "Alt"
      ],
      "key": "E"
    }
  ],
  "obsidian-hotkeys-for-templates:NEG.md": [
    {
      "modifiers": [
        "Alt"
      ],
      "key": "N"
    }
  ],
  "terminal:open-terminal-root.integrated": [
    {
      "modifiers": [
        "Mod"
      ],
      "key": "J"
    }
  ],
  "workspace:split-vertical": [
    {
      "modifiers": [
        "Mod"
      ],
      "key": "\\"
    }
  ],
  "obsidian-editor-shortcuts:duplicateLine": [],
  "obsidian-editor-shortcuts:insertLineAbove": [],
  "obsidian-editor-shortcuts:insertLineBelow": [],
  "obsidian-editor-shortcuts:joinLines": [],
  "command-palette:open": [
    {
      "modifiers": [
        "Mod",
        "Shift"
      ],
      "key": "P"
    },
    {
      "modifiers": [],
      "key": "F9"
    }
  ],
  "editor:delete-paragraph": [],
  "editor:swap-line-down": [
    {
      "modifiers": [
        "Alt"
      ],
      "key": "ArrowDown"
    }
  ],
  "editor:open-link-in-new-leaf": [],
  "obsidian-reminder-plugin:show-date-chooser": [],
  "obsidian-reminder-plugin:toggle-checklist-status": [],
  "obsidian-advanced-slides:reload-advanced-slides-preview": [
    {
      "modifiers": [
        "Shift"
      ],
      "key": "F5"
    }
  ],
  "file-explorer:new-file": [],
  "workspace:new-tab": [
    {
      "modifiers": [
        "Mod"
      ],
      "key": "T"
    }
  ],
  "editor:open-link-in-new-window": [],
  "table-editor-obsidian:format-all-tables": [
    {
      "modifiers": [
        "Alt",
        "Shift"
      ],
      "key": "F"
    }
  ],
  "workspace:move-to-new-window": [
    {
      "modifiers": [
        "Alt"
      ],
      "key": "W"
    }
  ],
  "obsidian-pangu:pangu-format": [
    {
      "modifiers": [
        "Mod",
        "Shift"
      ],
      "key": "S"
    }
  ],
  "table-editor-obsidian:escape-table": [
    {
      "modifiers": [
        "Shift"
      ],
      "key": "Enter"
    }
  ],
  "global-search:open": [],
  "khoj:search": [
    {
      "modifiers": [
        "Mod",
        "Shift"
      ],
      "key": "F"
    }
  ],
  "obsidian-editor-shortcuts:selectAllOccurrences": [],
  "obsidian-shellcommands:shell-command-hboli1opht": [
    {
      "modifiers": [],
      "key": "F5"
    }
  ],
  "obsidian-shellcommands:shell-command-eucwtglnz2": [
    {
      "modifiers": [
        "Mod"
      ],
      "key": "J"
    }
  ],
  "markdown:toggle-preview": [],
  "editor:toggle-checklist-status": [
    {
      "modifiers": [
        "Mod"
      ],
      "key": "Enter"
    }
  ],
  "insert-template": [
    {
      "modifiers": [],
      "key": "F12"
    }
  ],
  "obsidian-another-quick-switcher:grep": [
    {
      "modifiers": [],
      "key": "F3"
    }
  ],
  "app:open-help": [],
  "quick-explorer:browse-vault": [
    {
      "modifiers": [],
      "key": "F10"
    }
  ],
  "obsidian-advanced-new-file:advanced-new-file": [
    {
      "modifiers": [
        "Mod"
      ],
      "key": "N"
    }
  ],
  "markdown:add-metadata-property": [],
  "omnisearch:show-modal": [
    {
      "modifiers": [],
      "key": "F8"
    }
  ],
  "obsidian-kanban:toggle-kanban-view": [
    {
      "modifiers": [],
      "key": "F1"
    }
  ],
  "workspace:next-tab": [
    {
      "modifiers": [
        "Ctrl"
      ],
      "key": "Tab"
    }
  ],
  "text-snippets-obsidian:text-snippets": [
    {
      "modifiers": [
        "Shift"
      ],
      "key": "Tab"
    }
  ],
  "homepage:open-homepage": [
    {
      "modifiers": [
        "Mod"
      ],
      "key": "Home"
    }
  ]
}