{"Attention":["记录上周的一个IDEA.md"],"CSS":["blog-from-scratch.md"],"HTML":["blog-from-scratch.md"],"I":["Recent-works-review.md","blog-from-scratch.md"],"I tried to construct a blog site without frontend stack, only using browser-native CSS, HTML, and javascript. ":["blog-from-scratch.md"],"Idea":["记录上周的一个IDEA.md"],"New":["记录上周的一个IDEA.md"],"New Idea on Sparse Attention":["记录上周的一个IDEA.md"],"RPC":["rpc-server.md"],"Several":["rust-vs-cpp.md"],"Several things that make system engineering more pleasurable.":["rust-vs-cpp.md"],"Sparse":["记录上周的一个IDEA.md"],"The":["forward-forward.md"],"The idea is simple: a hidden layer's job is to extract good enough feature. ":["forward-forward.md"],"Things":["Recent-works-review.md"],"Things that I'm recently working on.":["Recent-works-review.md"],"Try":["rpc-server.md"],"Try to implement an RPC server from scratch. ":["rpc-server.md"],"a":["forward-forward.md","blog-from-scratch.md"],"an":["rpc-server.md"],"and":["blog-from-scratch.md"],"blog":["blog-from-scratch.md"],"browser":["blog-from-scratch.md"],"construct":["blog-from-scratch.md"],"engineering":["rust-vs-cpp.md"],"enough":["forward-forward.md"],"extract":["forward-forward.md"],"feature":["forward-forward.md"],"from":["rpc-server.md"],"frontend":["blog-from-scratch.md"],"good":["forward-forward.md"],"hidden":["forward-forward.md"],"idea":["forward-forward.md"],"implement":["rpc-server.md"],"is":["forward-forward.md"],"javascript":["blog-from-scratch.md"],"job":["forward-forward.md"],"layer":["forward-forward.md"],"m":["Recent-works-review.md"],"make":["rust-vs-cpp.md"],"more":["rust-vs-cpp.md"],"native":["blog-from-scratch.md"],"on":["记录上周的一个IDEA.md","Recent-works-review.md"],"only":["blog-from-scratch.md"],"pleasurable":["rust-vs-cpp.md"],"recently":["Recent-works-review.md"],"s":["forward-forward.md"],"scratch":["rpc-server.md"],"server":["rpc-server.md"],"simple":["forward-forward.md"],"site":["blog-from-scratch.md"],"stack":["blog-from-scratch.md"],"system":["rust-vs-cpp.md"],"that":["rust-vs-cpp.md","Recent-works-review.md"],"things":["rust-vs-cpp.md"],"to":["forward-forward.md","blog-from-scratch.md","rpc-server.md"],"tried":["blog-from-scratch.md"],"using":["blog-from-scratch.md"],"without":["blog-from-scratch.md"],"working":["Recent-works-review.md"]}